formalmath/__init__.py
formalmath/metamath/__init__.py
formalmath/metamath/core.py
formalmath-0.1.3.dist-info/licenses/LICENSE.txt
formalmath-0.1.3.dist-info/METADATA
formalmath-0.1.3.dist-info/WHEEL
formalmath-0.1.3.dist-info/top_level.txt
formalmath-0.1.3.dist-info/RECORD
