Metadata-Version: 2.4
Name: formalmath
Version: 0.1.3
Summary: A modular formal mathematics systems library, including Metamath
Author-email: Li Xiang <lx20150211@gmail.com>
License-Expression: MIT
Project-URL: Homepage, https://github.com/lixiang90/formalmath
Project-URL: Repository, https://github.com/lixiang90/formalmath
Keywords: formal system,metamath,logic,proof assistant
Classifier: Programming Language :: Python :: 3
Classifier: Operating System :: OS Independent
Classifier: Intended Audience :: Science/Research
Classifier: Topic :: Scientific/Engineering :: Mathematics
Requires-Python: >=3.7
License-File: LICENSE.txt
Dynamic: license-file
